os_diskconfig_python_novaclient_ext-0.1.3.dist-info/METADATA
os_diskconfig_python_novaclient_ext-0.1.3.dist-info/RECORD
os_diskconfig_python_novaclient_ext-0.1.3.dist-info/top_level.txt
os_diskconfig_python_novaclient_ext-0.1.3.dist-info/DESCRIPTION.rst
os_diskconfig_python_novaclient_ext-0.1.3.dist-info/metadata.json
os_diskconfig_python_novaclient_ext-0.1.3.dist-info/WHEEL
os_diskconfig_python_novaclient_ext/__init__.py
