Metadata-Version: 2.0
Name: os-diskconfig-python-novaclient-ext
Version: 0.1.3
Summary: Disk Config extension for python-novaclient
Home-page: UNKNOWN
Author: Rackspace
Author-email: rick.harris@rackspace.com
License: Apache License, Version 2.0
Platform: UNKNOWN
Classifier: Development Status :: 5 - Production/Stable
Classifier: Intended Audience :: Developers
Classifier: Intended Audience :: Information Technology
Classifier: License :: OSI Approved :: Apache Software License
Classifier: Operating System :: OS Independent
Classifier: Programming Language :: Python
Requires-Dist: python-novaclient
